{"lib/assets/Maske01.jpg":["lib/assets/Maske01.jpg"],"lib/assets/Maske02.jpg":["lib/assets/Maske02.jpg"],"lib/assets/Maske04.jpg":["lib/assets/Maske04.jpg"],"lib/assets/Maske05.jpg":["lib/assets/Maske05.jpg"],"lib/assets/Maske06.jpg":["lib/assets/Maske06.jpg"],"lib/assets/dalis_bilgisari01.jpg":["lib/assets/dalis_bilgisari01.jpg"],"lib/assets/dalis_bilgisari02.jpg":["lib/assets/dalis_bilgisari02.jpg"],"lib/assets/dalis_bilgisari03.jpg":["lib/assets/dalis_bilgisari03.jpg"],"lib/assets/dalis_elbise01.jpg":["lib/assets/dalis_elbise01.jpg"],"lib/assets/dalis_elbise02.jpg":["lib/assets/dalis_elbise02.jpg"],"lib/assets/dalis_elbise03.jpg":["lib/assets/dalis_elbise03.jpg"],"lib/assets/dalis_elbise04.jpg":["lib/assets/dalis_elbise04.jpg"],"lib/assets/dalis_elbise05.jpg":["lib/assets/dalis_elbise05.jpg"],"lib/assets/dalis_elbise06.jpg":["lib/assets/dalis_elbise06.jpg"],"lib/assets/denge_yelegi01.jpg":["lib/assets/denge_yelegi01.jpg"],"lib/assets/denge_yelegi02.jpg":["lib/assets/denge_yelegi02.jpg"],"lib/assets/denge_yelegi03.jpg":["lib/assets/denge_yelegi03.jpg"],"lib/assets/denge_yelegi04.jpg":["lib/assets/denge_yelegi04.jpg"],"lib/assets/maske03.jpg":["lib/assets/maske03.jpg"],"lib/assets/palet01.jpg":["lib/assets/palet01.jpg"],"lib/assets/palet02.jpg":["lib/assets/palet02.jpg"],"lib/assets/palet03.jpg":["lib/assets/palet03.jpg"],"lib/assets/regulator01.jpg":["lib/assets/regulator01.jpg"],"lib/assets/regulator02.jpg":["lib/assets/regulator02.jpg"],"lib/assets/regulator03.jpg":["lib/assets/regulator03.jpg"],"lib/assets/regulator04.jpg":["lib/assets/regulator04.jpg"],"lib/assets/regulator05.jpg":["lib/assets/regulator05.jpg"],"lib/assets/scuba.jpg":["lib/assets/scuba.jpg"],"lib/assets/set01.jpg":["lib/assets/set01.jpg"],"lib/assets/set02.jpg":["lib/assets/set02.jpg"],"lib/assets/set03.jpg":["lib/assets/set03.jpg"],"packages/cupertino_icons/assets/CupertinoIcons.ttf":["packages/cupertino_icons/assets/CupertinoIcons.ttf"],"packages/font_awesome_flutter/lib/fonts/fa-brands-400.ttf":["packages/font_awesome_flutter/lib/fonts/fa-brands-400.ttf"],"packages/font_awesome_flutter/lib/fonts/fa-regular-400.ttf":["packages/font_awesome_flutter/lib/fonts/fa-regular-400.ttf"],"packages/font_awesome_flutter/lib/fonts/fa-solid-900.ttf":["packages/font_awesome_flutter/lib/fonts/fa-solid-900.ttf"]}